shapreg/__init__.py
shapreg/games.py
shapreg/plotting.py
shapreg/removal.py
shapreg/shapley.py
shapreg/shapley_sampling.py
shapreg/shapley_unbiased.py
shapreg/stochastic_games.py
shapreg/utils.py
shapley_regression-0.0.1.dist-info/LICENSE
shapley_regression-0.0.1.dist-info/METADATA
shapley_regression-0.0.1.dist-info/WHEEL
shapley_regression-0.0.1.dist-info/top_level.txt
shapley_regression-0.0.1.dist-info/RECORD
