Metadata-Version: 2.1
Name: shapley-regression
Version: 0.0.1
Summary: For estimating Shapley values via linear regression.
Home-page: https://github.com/iancovert/shapley-regression
Author: Ian Covert
Author-email: icovert@cs.washington.edu
License: UNKNOWN
Platform: UNKNOWN
Classifier: Programming Language :: Python :: 3
Classifier: License :: OSI Approved :: MIT License
Classifier: Operating System :: OS Independent
Classifier: Intended Audience :: Science/Research
Classifier: Topic :: Scientific/Engineering
Requires-Python: >=3.6
License-File: LICENSE
Requires-Dist: numpy
Requires-Dist: scipy
Requires-Dist: tqdm
Requires-Dist: matplotlib
